caenhv/__init__.py
caenhv/version.py
caenhv/commands/__init__.py
caenhv/commands/channel.py
caenhv/commands/module.py
caenhv/devices/__init__.py
caenhv/devices/caenhv.py
caenhv/devices/channel.py
caenhv/devices/module.py
caenhv-0.0.1.dist-info/METADATA
caenhv-0.0.1.dist-info/WHEEL
caenhv-0.0.1.dist-info/RECORD
