Metadata-Version: 2.1
Name: caenhv
Version: 0.0.1
Summary: An unofficial Python package 🐍📦 to interface with CAEN high voltage power supplies
Project-URL: Download, https://github.com/lobis/caen-hv/releases
Project-URL: Homepage, https://github.com/lobis/caen-hv
Project-URL: Bug Tracker, https://github.com/lobis/caen-hv/issues
Author-email: Luis Antonio Obis Aparicio <luis.antonio.obis@gmail.com>
Classifier: Operating System :: OS Independent
Classifier: Programming Language :: Python :: 3
Requires-Python: >=3.8
Requires-Dist: pyserial
Provides-Extra: test
Requires-Dist: pytest; extra == 'test'
